{"_UNVERIFIED":"Fetched from Sefaria (Miqra according to the Masorah), nikud/teamim stripped mechanically - NOT hand-verified against a printed tikkun. Do not write from this text until 'verified' is flipped to true by the sofer.","verified":false,"sefer":"Deuteronomy","seferHe":"דברים","parsha":"Devarim","parshaHe":"דברים","sefariaRef":"Deuteronomy 1:1-3:22","wordCount":1548,"verses":[{"c":1,"v":1,"words":["אלה","הדברים","אשר","דבר","משה","אל","כל","ישראל","בעבר","הירדן","במדבר","בערבה","מול","סוף","בין","פארן","ובין","תפל","ולבן","וחצרת","ודי","זהב"]},{"c":1,"v":2,"words":["אחד","עשר","יום","מחרב","דרך","הר","שעיר","עד","קדש","ברנע"]},{"c":1,"v":3,"words":["ויהי","בארבעים","שנה","בעשתי","עשר","חדש","באחד","לחדש","דבר","משה","אל","בני","ישראל","ככל","אשר","צוה","יהוה","אתו","אלהם"]},{"c":1,"v":4,"words":["אחרי","הכתו","את","סיחן","מלך","האמרי","אשר","יושב","בחשבון","ואת","עוג","מלך","הבשן","אשר","יושב","בעשתרת","באדרעי"]},{"c":1,"v":5,"words":["בעבר","הירדן","בארץ","מואב","הואיל","משה","באר","את","התורה","הזאת","לאמר"]},{"c":1,"v":6,"words":["יהוה","אלהינו","דבר","אלינו","בחרב","לאמר","רב","לכם","שבת","בהר","הזה"]},{"c":1,"v":7,"words":["פנו","וסעו","לכם","ובאו","הר","האמרי","ואל","כל","שכניו","בערבה","בהר","ובשפלה","ובנגב","ובחוף","הים","ארץ","הכנעני","והלבנון","עד","הנהר","הגדל","נהר","פרת"]},{"c":1,"v":8,"words":["ראה","נתתי","לפניכם","את","הארץ","באו","ורשו","את","הארץ","אשר","נשבע","יהוה","לאבתיכם","לאברהם","ליצחק","וליעקב","לתת","להם","ולזרעם","אחריהם"]},{"c":1,"v":9,"words":["ואמר","אלכם","בעת","ההוא","לאמר","לא","אוכל","לבדי","שאת","אתכם"]},{"c":1,"v":10,"words":["יהוה","אלהיכם","הרבה","אתכם","והנכם","היום","ככוכבי","השמים","לרב"]},{"c":1,"v":11,"words":["יהוה","אלהי","אבותכם","יסף","עליכם","ככם","אלף","פעמים","ויברך","אתכם","כאשר","דבר","לכם"]},{"c":1,"v":12,"words":["איכה","אשא","לבדי","טרחכם","ומשאכם","וריבכם"]},{"c":1,"v":13,"words":["הבו","לכם","אנשים","חכמים","ונבנים","וידעים","לשבטיכם","ואשימם","בראשיכם"]},{"c":1,"v":14,"words":["ותענו","אתי","ותאמרו","טוב","הדבר","אשר","דברת","לעשות"]},{"c":1,"v":15,"words":["ואקח","את","ראשי","שבטיכם","אנשים","חכמים","וידעים","ואתן","אותם","ראשים","עליכם","שרי","אלפים","ושרי","מאות","ושרי","חמשים","ושרי","עשרת","ושטרים","לשבטיכם"]},{"c":1,"v":16,"words":["ואצוה","את","שפטיכם","בעת","ההוא","לאמר","שמע","בין","אחיכם","ושפטתם","צדק","בין","איש","ובין","אחיו","ובין","גרו"]},{"c":1,"v":17,"words":["לא","תכירו","פנים","במשפט","כקטן","כגדל","תשמעון","לא","תגורו","מפני","איש","כי","המשפט","לאלהים","הוא","והדבר","אשר","יקשה","מכם","תקרבון","אלי","ושמעתיו"]},{"c":1,"v":18,"words":["ואצוה","אתכם","בעת","ההוא","את","כל","הדברים","אשר","תעשון"]},{"c":1,"v":19,"words":["ונסע","מחרב","ונלך","את","כל","המדבר","הגדול","והנורא","ההוא","אשר","ראיתם","דרך","הר","האמרי","כאשר","צוה","יהוה","אלהינו","אתנו","ונבא","עד","קדש","ברנע"]},{"c":1,"v":20,"words":["ואמר","אלכם","באתם","עד","הר","האמרי","אשר","יהוה","אלהינו","נתן","לנו"]},{"c":1,"v":21,"words":["ראה","נתן","יהוה","אלהיך","לפניך","את","הארץ","עלה","רש","כאשר","דבר","יהוה","אלהי","אבתיך","לך","אל","תירא","ואל","תחת"]},{"c":1,"v":22,"words":["ותקרבון","אלי","כלכם","ותאמרו","נשלחה","אנשים","לפנינו","ויחפרו","לנו","את","הארץ","וישבו","אתנו","דבר","את","הדרך","אשר","נעלה","בה","ואת","הערים","אשר","נבא","אליהן"]},{"c":1,"v":23,"words":["וייטב","בעיני","הדבר","ואקח","מכם","שנים","עשר","אנשים","איש","אחד","לשבט"]},{"c":1,"v":24,"words":["ויפנו","ויעלו","ההרה","ויבאו","עד","נחל","אשכל","וירגלו","אתה"]},{"c":1,"v":25,"words":["ויקחו","בידם","מפרי","הארץ","ויורדו","אלינו","וישבו","אתנו","דבר","ויאמרו","טובה","הארץ","אשר","יהוה","אלהינו","נתן","לנו"]},{"c":1,"v":26,"words":["ולא","אביתם","לעלת","ותמרו","את","פי","יהוה","אלהיכם"]},{"c":1,"v":27,"words":["ותרגנו","באהליכם","ותאמרו","בשנאת","יהוה","אתנו","הוציאנו","מארץ","מצרים","לתת","אתנו","ביד","האמרי","להשמידנו"]},{"c":1,"v":28,"words":["אנה","אנחנו","עלים","אחינו","המסו","את","לבבנו","לאמר","עם","גדול","ורם","ממנו","ערים","גדלת","ובצורת","בשמים","וגם","בני","ענקים","ראינו","שם"]},{"c":1,"v":29,"words":["ואמר","אלכם","לא","תערצון","ולא","תיראון","מהם"]},{"c":1,"v":30,"words":["יהוה","אלהיכם","ההלך","לפניכם","הוא","ילחם","לכם","ככל","אשר","עשה","אתכם","במצרים","לעיניכם"]},{"c":1,"v":31,"words":["ובמדבר","אשר","ראית","אשר","נשאך","יהוה","אלהיך","כאשר","ישא","איש","את","בנו","בכל","הדרך","אשר","הלכתם","עד","באכם","עד","המקום","הזה"]},{"c":1,"v":32,"words":["ובדבר","הזה","אינכם","מאמינם","ביהוה","אלהיכם"]},{"c":1,"v":33,"words":["ההלך","לפניכם","בדרך","לתור","לכם","מקום","לחנתכם","באש","לילה","לראתכם","בדרך","אשר","תלכו","בה","ובענן","יומם"]},{"c":1,"v":34,"words":["וישמע","יהוה","את","קול","דבריכם","ויקצף","וישבע","לאמר"]},{"c":1,"v":35,"words":["אם","יראה","איש","באנשים","האלה","הדור","הרע","הזה","את","הארץ","הטובה","אשר","נשבעתי","לתת","לאבתיכם"]},{"c":1,"v":36,"words":["זולתי","כלב","בן","יפנה","הוא","יראנה","ולו","אתן","את","הארץ","אשר","דרך","בה","ולבניו","יען","אשר","מלא","אחרי","יהוה"]},{"c":1,"v":37,"words":["גם","בי","התאנף","יהוה","בגללכם","לאמר","גם","אתה","לא","תבא","שם"]},{"c":1,"v":38,"words":["יהושע","בן","נון","העמד","לפניך","הוא","יבא","שמה","אתו","חזק","כי","הוא","ינחלנה","את","ישראל"]},{"c":1,"v":39,"words":["וטפכם","אשר","אמרתם","לבז","יהיה","ובניכם","אשר","לא","ידעו","היום","טוב","ורע","המה","יבאו","שמה","ולהם","אתננה","והם","יירשוה"]},{"c":1,"v":40,"words":["ואתם","פנו","לכם","וסעו","המדברה","דרך","ים","סוף"]},{"c":1,"v":41,"words":["ותענו","ותאמרו","אלי","חטאנו","ליהוה","אנחנו","נעלה","ונלחמנו","ככל","אשר","צונו","יהוה","אלהינו","ותחגרו","איש","את","כלי","מלחמתו","ותהינו","לעלת","ההרה"]},{"c":1,"v":42,"words":["ויאמר","יהוה","אלי","אמר","להם","לא","תעלו","ולא","תלחמו","כי","אינני","בקרבכם","ולא","תנגפו","לפני","איביכם"]},{"c":1,"v":43,"words":["ואדבר","אליכם","ולא","שמעתם","ותמרו","את","פי","יהוה","ותזדו","ותעלו","ההרה"]},{"c":1,"v":44,"words":["ויצא","האמרי","הישב","בהר","ההוא","לקראתכם","וירדפו","אתכם","כאשר","תעשינה","הדברים","ויכתו","אתכם","בשעיר","עד","חרמה"]},{"c":1,"v":45,"words":["ותשבו","ותבכו","לפני","יהוה","ולא","שמע","יהוה","בקלכם","ולא","האזין","אליכם"]},{"c":1,"v":46,"words":["ותשבו","בקדש","ימים","רבים","כימים","אשר","ישבתם"]},{"c":2,"v":1,"words":["ונפן","ונסע","המדברה","דרך","ים","סוף","כאשר","דבר","יהוה","אלי","ונסב","את","הר","שעיר","ימים","רבים"]},{"c":2,"v":2,"words":["ויאמר","יהוה","אלי","לאמר"]},{"c":2,"v":3,"words":["רב","לכם","סב","את","ההר","הזה","פנו","לכם","צפנה"]},{"c":2,"v":4,"words":["ואת","העם","צו","לאמר","אתם","עברים","בגבול","אחיכם","בני","עשו","הישבים","בשעיר","וייראו","מכם","ונשמרתם","מאד"]},{"c":2,"v":5,"words":["אל","תתגרו","בם","כי","לא","אתן","לכם","מארצם","עד","מדרך","כף","רגל","כי","ירשה","לעשו","נתתי","את","הר","שעיר"]},{"c":2,"v":6,"words":["אכל","תשברו","מאתם","בכסף","ואכלתם","וגם","מים","תכרו","מאתם","בכסף","ושתיתם"]},{"c":2,"v":7,"words":["כי","יהוה","אלהיך","ברכך","בכל","מעשה","ידך","ידע","לכתך","את","המדבר","הגדל","הזה","זה","ארבעים","שנה","יהוה","אלהיך","עמך","לא","חסרת","דבר"]},{"c":2,"v":8,"words":["ונעבר","מאת","אחינו","בני","עשו","הישבים","בשעיר","מדרך","הערבה","מאילת","ומעצין","גבר","ונפן","ונעבר","דרך","מדבר","מואב"]},{"c":2,"v":9,"words":["ויאמר","יהוה","אלי","אל","תצר","את","מואב","ואל","תתגר","בם","מלחמה","כי","לא","אתן","לך","מארצו","ירשה","כי","לבני","לוט","נתתי","את","ער","ירשה"]},{"c":2,"v":10,"words":["האמים","לפנים","ישבו","בה","עם","גדול","ורב","ורם","כענקים"]},{"c":2,"v":11,"words":["רפאים","יחשבו","אף","הם","כענקים","והמאבים","יקראו","להם","אמים"]},{"c":2,"v":12,"words":["ובשעיר","ישבו","החרים","לפנים","ובני","עשו","יירשום","וישמידום","מפניהם","וישבו","תחתם","כאשר","עשה","ישראל","לארץ","ירשתו","אשר","נתן","יהוה","להם"]},{"c":2,"v":13,"words":["עתה","קמו","ועברו","לכם","את","נחל","זרד","ונעבר","את","נחל","זרד"]},{"c":2,"v":14,"words":["והימים","אשר","הלכנו","מקדש","ברנע","עד","אשר","עברנו","את","נחל","זרד","שלשים","ושמנה","שנה","עד","תם","כל","הדור","אנשי","המלחמה","מקרב","המחנה","כאשר","נשבע","יהוה","להם"]},{"c":2,"v":15,"words":["וגם","יד","יהוה","היתה","בם","להמם","מקרב","המחנה","עד","תמם"]},{"c":2,"v":16,"words":["ויהי","כאשר","תמו","כל","אנשי","המלחמה","למות","מקרב","העם"]},{"c":2,"v":17,"words":["וידבר","יהוה","אלי","לאמר"]},{"c":2,"v":18,"words":["אתה","עבר","היום","את","גבול","מואב","את","ער"]},{"c":2,"v":19,"words":["וקרבת","מול","בני","עמון","אל","תצרם","ואל","תתגר","בם","כי","לא","אתן","מארץ","בני","עמון","לך","ירשה","כי","לבני","לוט","נתתיה","ירשה"]},{"c":2,"v":20,"words":["ארץ","רפאים","תחשב","אף","הוא","רפאים","ישבו","בה","לפנים","והעמנים","יקראו","להם","זמזמים"]},{"c":2,"v":21,"words":["עם","גדול","ורב","ורם","כענקים","וישמידם","יהוה","מפניהם","ויירשם","וישבו","תחתם"]},{"c":2,"v":22,"words":["כאשר","עשה","לבני","עשו","הישבים","בשעיר","אשר","השמיד","את","החרי","מפניהם","ויירשם","וישבו","תחתם","עד","היום","הזה"]},{"c":2,"v":23,"words":["והעוים","הישבים","בחצרים","עד","עזה","כפתרים","היצאים","מכפתר","השמידם","וישבו","תחתם"]},{"c":2,"v":24,"words":["קומו","סעו","ועברו","את","נחל","ארנן","ראה","נתתי","בידך","את","סיחן","מלך","חשבון","האמרי","ואת","ארצו","החל","רש","והתגר","בו","מלחמה"]},{"c":2,"v":25,"words":["היום","הזה","אחל","תת","פחדך","ויראתך","על","פני","העמים","תחת","כל","השמים","אשר","ישמעון","שמעך","ורגזו","וחלו","מפניך"]},{"c":2,"v":26,"words":["ואשלח","מלאכים","ממדבר","קדמות","אל","סיחון","מלך","חשבון","דברי","שלום","לאמר"]},{"c":2,"v":27,"words":["אעברה","בארצך","בדרך","בדרך","אלך","לא","אסור","ימין","ושמאול"]},{"c":2,"v":28,"words":["אכל","בכסף","תשברני","ואכלתי","ומים","בכסף","תתן","לי","ושתיתי","רק","אעברה","ברגלי"]},{"c":2,"v":29,"words":["כאשר","עשו","לי","בני","עשו","הישבים","בשעיר","והמואבים","הישבים","בער","עד","אשר","אעבר","את","הירדן","אל","הארץ","אשר","יהוה","אלהינו","נתן","לנו"]},{"c":2,"v":30,"words":["ולא","אבה","סיחן","מלך","חשבון","העברנו","בו","כי","הקשה","יהוה","אלהיך","את","רוחו","ואמץ","את","לבבו","למען","תתו","בידך","כיום","הזה"]},{"c":2,"v":31,"words":["ויאמר","יהוה","אלי","ראה","החלתי","תת","לפניך","את","סיחן","ואת","ארצו","החל","רש","לרשת","את","ארצו"]},{"c":2,"v":32,"words":["ויצא","סיחן","לקראתנו","הוא","וכל","עמו","למלחמה","יהצה"]},{"c":2,"v":33,"words":["ויתנהו","יהוה","אלהינו","לפנינו","ונך","אתו","ואת","בנו","ואת","כל","עמו"]},{"c":2,"v":34,"words":["ונלכד","את","כל","עריו","בעת","ההוא","ונחרם","את","כל","עיר","מתם","והנשים","והטף","לא","השארנו","שריד"]},{"c":2,"v":35,"words":["רק","הבהמה","בזזנו","לנו","ושלל","הערים","אשר","לכדנו"]},{"c":2,"v":36,"words":["מערער","אשר","על","שפת","נחל","ארנן","והעיר","אשר","בנחל","ועד","הגלעד","לא","היתה","קריה","אשר","שגבה","ממנו","את","הכל","נתן","יהוה","אלהינו","לפנינו"]},{"c":2,"v":37,"words":["רק","אל","ארץ","בני","עמון","לא","קרבת","כל","יד","נחל","יבק","וערי","ההר","וכל","אשר","צוה","יהוה","אלהינו"]},{"c":3,"v":1,"words":["ונפן","ונעל","דרך","הבשן","ויצא","עוג","מלך","הבשן","לקראתנו","הוא","וכל","עמו","למלחמה","אדרעי"]},{"c":3,"v":2,"words":["ויאמר","יהוה","אלי","אל","תירא","אתו","כי","בידך","נתתי","אתו","ואת","כל","עמו","ואת","ארצו","ועשית","לו","כאשר","עשית","לסיחן","מלך","האמרי","אשר","יושב","בחשבון"]},{"c":3,"v":3,"words":["ויתן","יהוה","אלהינו","בידנו","גם","את","עוג","מלך","הבשן","ואת","כל","עמו","ונכהו","עד","בלתי","השאיר","לו","שריד"]},{"c":3,"v":4,"words":["ונלכד","את","כל","עריו","בעת","ההוא","לא","היתה","קריה","אשר","לא","לקחנו","מאתם","ששים","עיר","כל","חבל","ארגב","ממלכת","עוג","בבשן"]},{"c":3,"v":5,"words":["כל","אלה","ערים","בצרת","חומה","גבהה","דלתים","ובריח","לבד","מערי","הפרזי","הרבה","מאד"]},{"c":3,"v":6,"words":["ונחרם","אותם","כאשר","עשינו","לסיחן","מלך","חשבון","החרם","כל","עיר","מתם","הנשים","והטף"]},{"c":3,"v":7,"words":["וכל","הבהמה","ושלל","הערים","בזונו","לנו"]},{"c":3,"v":8,"words":["ונקח","בעת","ההוא","את","הארץ","מיד","שני","מלכי","האמרי","אשר","בעבר","הירדן","מנחל","ארנן","עד","הר","חרמון"]},{"c":3,"v":9,"words":["צידנים","יקראו","לחרמון","שרין","והאמרי","יקראו","לו","שניר"]},{"c":3,"v":10,"words":["כל","ערי","המישר","וכל","הגלעד","וכל","הבשן","עד","סלכה","ואדרעי","ערי","ממלכת","עוג","בבשן"]},{"c":3,"v":11,"words":["כי","רק","עוג","מלך","הבשן","נשאר","מיתר","הרפאים","הנה","ערשו","ערש","ברזל","הלה","הוא","ברבת","בני","עמון","תשע","אמות","ארכה","וארבע","אמות","רחבה","באמת","איש"]},{"c":3,"v":12,"words":["ואת","הארץ","הזאת","ירשנו","בעת","ההוא","מערער","אשר","על","נחל","ארנן","וחצי","הר","הגלעד","ועריו","נתתי","לראובני","ולגדי"]},{"c":3,"v":13,"words":["ויתר","הגלעד","וכל","הבשן","ממלכת","עוג","נתתי","לחצי","שבט","המנשה","כל","חבל","הארגב","לכל","הבשן","ההוא","יקרא","ארץ","רפאים"]},{"c":3,"v":14,"words":["יאיר","בן","מנשה","לקח","את","כל","חבל","ארגב","עד","גבול","הגשורי","והמעכתי","ויקרא","אתם","על","שמו","את","הבשן","חות","יאיר","עד","היום","הזה"]},{"c":3,"v":15,"words":["ולמכיר","נתתי","את","הגלעד"]},{"c":3,"v":16,"words":["ולראובני","ולגדי","נתתי","מן","הגלעד","ועד","נחל","ארנן","תוך","הנחל","וגבל","ועד","יבק","הנחל","גבול","בני","עמון"]},{"c":3,"v":17,"words":["והערבה","והירדן","וגבל","מכנרת","ועד","ים","הערבה","ים","המלח","תחת","אשדת","הפסגה","מזרחה"]},{"c":3,"v":18,"words":["ואצו","אתכם","בעת","ההוא","לאמר","יהוה","אלהיכם","נתן","לכם","את","הארץ","הזאת","לרשתה","חלוצים","תעברו","לפני","אחיכם","בני","ישראל","כל","בני","חיל"]},{"c":3,"v":19,"words":["רק","נשיכם","וטפכם","ומקנכם","ידעתי","כי","מקנה","רב","לכם","ישבו","בעריכם","אשר","נתתי","לכם"]},{"c":3,"v":20,"words":["עד","אשר","יניח","יהוה","לאחיכם","ככם","וירשו","גם","הם","את","הארץ","אשר","יהוה","אלהיכם","נתן","להם","בעבר","הירדן","ושבתם","איש","לירשתו","אשר","נתתי","לכם"]},{"c":3,"v":21,"words":["ואת","יהושוע","צויתי","בעת","ההוא","לאמר","עיניך","הראת","את","כל","אשר","עשה","יהוה","אלהיכם","לשני","המלכים","האלה","כן","יעשה","יהוה","לכל","הממלכות","אשר","אתה","עבר","שמה"]},{"c":3,"v":22,"words":["לא","תיראום","כי","יהוה","אלהיכם","הוא","הנלחם","לכם"]}]}